miguel_paquete/__init__.py
miguel_paquete/courses.py
miguel_paquete/utils.py
miguel_paquete-0.1.0.dist-info/METADATA
miguel_paquete-0.1.0.dist-info/WHEEL
miguel_paquete-0.1.0.dist-info/top_level.txt
miguel_paquete-0.1.0.dist-info/RECORD
