Metadata-Version: 2.1
Name: miguel_paquete
Version: 0.1.0
Summary: Consultar cursos
Author: Miguel Rodil
